Metadata-Version: 2.1
Name: odoo-addon-stock_buffer_capacity_limit
Version: 18.0.1.0.1
Requires-Python: >=3.10
Requires-Dist: odoo-addon-ddmrp==18.0.*
Requires-Dist: odoo==18.0.*
Summary: Ensures that the limits of storage are never surpassed
Home-page: https://github.com/OCA/ddmrp
License: LGPL-3
Author: ForgeFlow, Odoo Community Association (OCA)
Author-email: support@odoo-community.org
Classifier: Programming Language :: Python
Classifier: Framework :: Odoo
Classifier: Framework :: Odoo :: 18.0
Classifier: License :: OSI Approved :: GNU Lesser General Public License v3 (LGPLv3)
Classifier: Development Status :: 4 - Beta
